style_transfer/__init__.py
style_transfer/stylize.py
style_transfer/cyclegan/__init__.py
style_transfer/gatys/__init__.py
style_transfer/gatys/neural_style.py
style_transfer/gatys/neural_style_upload.py
style_transfer/gatys/neural_style_wrapper.py
style_transfer/gatys/nst.py
style_transfer/gatys/nst_utils2.py
style_transfer/gatys/rough.py
style_transfer-0.0.1.dist-info/LICENSE
style_transfer-0.0.1.dist-info/METADATA
style_transfer-0.0.1.dist-info/WHEEL
style_transfer-0.0.1.dist-info/top_level.txt
style_transfer-0.0.1.dist-info/RECORD
