Metadata-Version: 2.1
Name: style-transfer
Version: 0.0.1
Summary: A library for style transfer
Home-page: https://github.com/pypa/sampleproject
Author: Piyush Singh
Author-email: piyushsinghkgpian@gmail.com
License: UNKNOWN
Platform: UNKNOWN
Classifier: Programming Language :: Python :: 3
Classifier: License :: OSI Approved :: MIT License
Classifier: Operating System :: OS Independent
Requires-Dist: requests (==2.19.1)
Requires-Dist: tensorflow (==1.12.0)
Requires-Dist: matplotlib (==2.2.2)
